rest_wrapper/__init__.py
rest_wrapper/rest_wrapper.py
rest_wrapper/utilities/__init__.py
rest_wrapper/utilities/auth.py
rest_wrapper-0.0.3.dist-info/LICENSE.rst
rest_wrapper-0.0.3.dist-info/METADATA
rest_wrapper-0.0.3.dist-info/WHEEL
rest_wrapper-0.0.3.dist-info/RECORD
