Metadata-Version: 2.1
Name: rest-wrapper
Version: 0.0.3
Summary: Simple, extendable base rest client for python
Home-page: https://github.com/nat5142/rest-wrapper
Keywords: rest-wrapper
Author: Nick Tulli
Author-email: ntulli.dev@gmail.com
Requires-Python: >=3.8,<3.12
Classifier: Development Status :: 2 - Pre-Alpha
Classifier: Intended Audience :: Developers
Classifier: License :: OSI Approved :: MIT License
Classifier: Natural Language :: English
Classifier: Programming Language :: Python :: 3
Classifier: Programming Language :: Python :: 3.8
Classifier: Programming Language :: Python :: 3.9
Classifier: Programming Language :: Python :: 3.10
Classifier: Programming Language :: Python :: 3.11
Requires-Dist: requests (>=2.31.0,<3.0.0)
Project-URL: Bug Tracker, https://github.com/nat5142/rest-wrapper/issues
Project-URL: Documentation, https://rest-wrapper.readthedocs.io
Project-URL: Repository, https://github.com/nat5142/rest-wrapper
